Workbook

Sheet Resumen pool
A1: Estatus y proyección por pool — Periodo S37–S40
A2: Fuente: hoja base (ventas UG/WA/CAD/RN a S40; MOD B cargado a S39 parcial). Supuestos en hoja Parametros.
A4: Pool | B4: Dotación | C4: HC efectivo | D4: Venta PM | E4: Meta PM | F4: % PM | G4: CM real | H4: CM proyectado | I4: Meta CM | J4: % CM proy | K4: Cumpl. actual | L4: Cumpl. proyectado | M4: Desfase PM (und) | N4: Desfase CM (und) | O4: Activan | P4: Cerca (70-80%) | Q4: No activan | R4: % activación | S4: Carta (S/) | T4: Gasto actual (S/) | U4: Gasto proyectado (S/) | V4: % gasto / carta
A5: Inbound Premium | B5: =COUNTIF('Detalle asesor'!$B$2:$B$264,$A5) -> 44 | C5: =SUMIF('Detalle asesor'!$B$2:$B$264,$A5,'Detalle asesor'!$F$2:$F$264) -> 38.909091 | D5: =SUMIF('Detalle asesor'!$B$2:$B$264,$A5,'Detalle asesor'!$G$2:$G$264) -> 296 | E5: =SUMIF('Detalle asesor'!$B$2:$B$264,$A5,'Detalle asesor'!$H$2:$H$264) -> 622 | F5: =IFERROR(D5/E5,0) -> 0.47588424 | G5: =SUMIF('Detalle asesor'!$B$2:$B$264,$A5,'Detalle asesor'!$J$2:$J$264) -> 223 | H5: =SUMIF('Detalle asesor'!$B$2:$B$264,$A5,'Detalle asesor'!$N$2:$N$264) -> 381.59091 | I5: =SUMIF('Detalle asesor'!$B$2:$B$264,$A5,'Detalle asesor'!$O$2:$O$264) -> 212 | J5: =IFERROR(H5/I5,0) -> 1.7999571 | K5: =Parametros!$B$3*F5+Parametros!$B$4*IFERROR(G5/I5,0) -> 0.64868501 | L5: =Parametros!$B$3*F5+Parametros!$B$4*J5 -> 0.87310611 | M5: =D5-E5 -> -326 | N5: =H5-I5 -> 169.59091 | O5: =COUNTIFS('Detalle asesor'!$B$2:$B$264,$A5,'Detalle asesor'!$Z$2:$Z$264,"Activa") -> 26 | P5: =COUNTIFS('Detalle asesor'!$B$2:$B$264,$A5,'Detalle asesor'!$Z$2:$Z$264,"Cerca") -> 3 | Q5: =COUNTIFS('Detalle asesor'!$B$2:$B$264,$A5,'Detalle asesor'!$Z$2:$Z$264,"No activa") -> 15 | R5: =IFERROR(O5/B5,0) -> 0.59090909 | S5: =SUMIF('Detalle asesor'!$B$2:$B$264,$A5,'Detalle asesor'!$V$2:$V$264) -> 48490 | T5: =SUMIF('Detalle asesor'!$B$2:$B$264,$A5,'Detalle asesor'!$Y$2:$Y$264) -> 11640 | U5: =SUMIF('Detalle asesor'!$B$2:$B$264,$A5,'Detalle asesor'!$W$2:$W$264) -> 35015 | V5: =IFERROR(U5/S5,0) -> 0.72210765
A6: Inbound Regular | B6: =COUNTIF('Detalle asesor'!$B$2:$B$264,$A6) -> 27 | C6: =SUMIF('Detalle asesor'!$B$2:$B$264,$A6,'Detalle asesor'!$F$2:$F$264) -> 22.795455 | D6: =SUMIF('Detalle asesor'!$B$2:$B$264,$A6,'Detalle asesor'!$G$2:$G$264) -> 61 | E6: =SUMIF('Detalle asesor'!$B$2:$B$264,$A6,'Detalle asesor'!$H$2:$H$264) -> 227 | F6: =IFERROR(D6/E6,0) -> 0.26872247 | G6: =SUMIF('Detalle asesor'!$B$2:$B$264,$A6,'Detalle asesor'!$J$2:$J$264) -> 69 | H6: =SUMIF('Detalle asesor'!$B$2:$B$264,$A6,'Detalle asesor'!$N$2:$N$264) -> 108.68182 | I6: =SUMIF('Detalle asesor'!$B$2:$B$264,$A6,'Detalle asesor'!$O$2:$O$264) -> 95 | J6: =IFERROR(H6/I6,0) -> 1.1440191 | K6: =Parametros!$B$3*F6+Parametros!$B$4*IFERROR(G6/I6,0) -> 0.40600046 | L6: =Parametros!$B$3*F6+Parametros!$B$4*J6 -> 0.53131147 | M6: =D6-E6 -> -166 | N6: =H6-I6 -> 13.681818 | O6: =COUNTIFS('Detalle asesor'!$B$2:$B$264,$A6,'Detalle asesor'!$Z$2:$Z$264,"Activa") -> 5 | P6: =COUNTIFS('Detalle asesor'!$B$2:$B$264,$A6,'Detalle asesor'!$Z$2:$Z$264,"Cerca") -> 1 | Q6: =COUNTIFS('Detalle asesor'!$B$2:$B$264,$A6,'Detalle asesor'!$Z$2:$Z$264,"No activa") -> 21 | R6: =IFERROR(O6/B6,0) -> 0.18518519 | S6: =SUMIF('Detalle asesor'!$B$2:$B$264,$A6,'Detalle asesor'!$V$2:$V$264) -> 27355 | T6: =SUMIF('Detalle asesor'!$B$2:$B$264,$A6,'Detalle asesor'!$Y$2:$Y$264) -> 900 | U6: =SUMIF('Detalle asesor'!$B$2:$B$264,$A6,'Detalle asesor'!$W$2:$W$264) -> 5460 | V6: =IFERROR(U6/S6,0) -> 0.19959788
A7: Outbound Premium | B7: =COUNTIF('Detalle asesor'!$B$2:$B$264,$A7) -> 38 | C7: =SUMIF('Detalle asesor'!$B$2:$B$264,$A7,'Detalle asesor'!$F$2:$F$264) -> 35 | D7: =SUMIF('Detalle asesor'!$B$2:$B$264,$A7,'Detalle asesor'!$G$2:$G$264) -> 128 | E7: =SUMIF('Detalle asesor'!$B$2:$B$264,$A7,'Detalle asesor'!$H$2:$H$264) -> 250 | F7: =IFERROR(D7/E7,0) -> 0.512 | G7: =SUMIF('Detalle asesor'!$B$2:$B$264,$A7,'Detalle asesor'!$J$2:$J$264) -> 14 | H7: =SUMIF('Detalle asesor'!$B$2:$B$264,$A7,'Detalle asesor'!$N$2:$N$264) -> 27 | I7: =SUMIF('Detalle asesor'!$B$2:$B$264,$A7,'Detalle asesor'!$O$2:$O$264) -> 109 | J7: =IFERROR(H7/I7,0) -> 0.24770642 | K7: =Parametros!$B$3*F7+Parametros!$B$4*IFERROR(G7/I7,0) -> 0.39693211 | L7: =Parametros!$B$3*F7+Parametros!$B$4*J7 -> 0.43271193 | M7: =D7-E7 -> -122 | N7: =H7-I7 -> -82 | O7: =COUNTIFS('Detalle asesor'!$B$2:$B$264,$A7,'Detalle asesor'!$Z$2:$Z$264,"Activa") -> 5 | P7: =COUNTIFS('Detalle asesor'!$B$2:$B$264,$A7,'Detalle asesor'!$Z$2:$Z$264,"Cerca") -> 1 | Q7: =COUNTIFS('Detalle asesor'!$B$2:$B$264,$A7,'Detalle asesor'!$Z$2:$Z$264,"No activa") -> 32 | R7: =IFERROR(O7/B7,0) -> 0.13157895 | S7: =SUMIF('Detalle asesor'!$B$2:$B$264,$A7,'Detalle asesor'!$V$2:$V$264) -> 42000 | T7: =SUMIF('Detalle asesor'!$B$2:$B$264,$A7,'Detalle asesor'!$Y$2:$Y$264) -> 9960 | U7: =SUMIF('Detalle asesor'!$B$2:$B$264,$A7,'Detalle asesor'!$W$2:$W$264) -> 9960 | V7: =IFERROR(U7/S7,0) -> 0.23714286
A8: Outbound Regular | B8: =COUNTIF('Detalle asesor'!$B$2:$B$264,$A8) -> 41 | C8: =SUMIF('Detalle asesor'!$B$2:$B$264,$A8,'Detalle asesor'!$F$2:$F$264) -> 37.659091 | D8: =SUMIF('Detalle asesor'!$B$2:$B$264,$A8,'Detalle asesor'!$G$2:$G$264) -> 33 | E8: =SUMIF('Detalle asesor'!$B$2:$B$264,$A8,'Detalle asesor'!$H$2:$H$264) -> 174 | F8: =IFERROR(D8/E8,0) -> 0.18965517 | G8: =SUMIF('Detalle asesor'!$B$2:$B$264,$A8,'Detalle asesor'!$J$2:$J$264) -> 51 | H8: =SUMIF('Detalle asesor'!$B$2:$B$264,$A8,'Detalle asesor'!$N$2:$N$264) -> 89.5 | I8: =SUMIF('Detalle asesor'!$B$2:$B$264,$A8,'Detalle asesor'!$O$2:$O$264) -> 81 | J8: =IFERROR(H8/I8,0) -> 1.1049383 | K8: =Parametros!$B$3*F8+Parametros!$B$4*IFERROR(G8/I8,0) -> 0.32164751 | L8: =Parametros!$B$3*F8+Parametros!$B$4*J8 -> 0.4642401 | M8: =D8-E8 -> -141 | N8: =H8-I8 -> 8.5 | O8: =COUNTIFS('Detalle asesor'!$B$2:$B$264,$A8,'Detalle asesor'!$Z$2:$Z$264,"Activa") -> 13 | P8: =COUNTIFS('Detalle asesor'!$B$2:$B$264,$A8,'Detalle asesor'!$Z$2:$Z$264,"Cerca") -> 1 | Q8: =COUNTIFS('Detalle asesor'!$B$2:$B$264,$A8,'Detalle asesor'!$Z$2:$Z$264,"No activa") -> 27 | R8: =IFERROR(O8/B8,0) -> 0.31707317 | S8: =SUMIF('Detalle asesor'!$B$2:$B$264,$A8,'Detalle asesor'!$V$2:$V$264) -> 45191 | T8: =SUMIF('Detalle asesor'!$B$2:$B$264,$A8,'Detalle asesor'!$Y$2:$Y$264) -> 5220 | U8: =SUMIF('Detalle asesor'!$B$2:$B$264,$A8,'Detalle asesor'!$W$2:$W$264) -> 15540 | V8: =IFERROR(U8/S8,0) -> 0.34387378
A9: Chattigo | B9: =COUNTIF('Detalle asesor'!$B$2:$B$264,$A9) -> 18 | C9: =SUMIF('Detalle asesor'!$B$2:$B$264,$A9,'Detalle asesor'!$F$2:$F$264) -> 15.295455 | D9: =SUMIF('Detalle asesor'!$B$2:$B$264,$A9,'Detalle asesor'!$G$2:$G$264) -> 228 | E9: =SUMIF('Detalle asesor'!$B$2:$B$264,$A9,'Detalle asesor'!$H$2:$H$264) -> 459 | F9: =IFERROR(D9/E9,0) -> 0.49673203 | G9: =SUMIF('Detalle asesor'!$B$2:$B$264,$A9,'Detalle asesor'!$J$2:$J$264) -> 175 | H9: =SUMIF('Detalle asesor'!$B$2:$B$264,$A9,'Detalle asesor'!$N$2:$N$264) -> 304.34545 | I9: =SUMIF('Detalle asesor'!$B$2:$B$264,$A9,'Detalle asesor'!$O$2:$O$264) -> 164 | J9: =IFERROR(H9/I9,0) -> 1.855765 | K9: =Parametros!$B$3*F9+Parametros!$B$4*IFERROR(G9/I9,0) -> 0.66783437 | L9: =Parametros!$B$3*F9+Parametros!$B$4*J9 -> 0.90444191 | M9: =D9-E9 -> -231 | N9: =H9-I9 -> 140.34545 | O9: =COUNTIFS('Detalle asesor'!$B$2:$B$264,$A9,'Detalle asesor'!$Z$2:$Z$264,"Activa") -> 11 | P9: =COUNTIFS('Detalle asesor'!$B$2:$B$264,$A9,'Detalle asesor'!$Z$2:$Z$264,"Cerca") -> 2 | Q9: =COUNTIFS('Detalle asesor'!$B$2:$B$264,$A9,'Detalle asesor'!$Z$2:$Z$264,"No activa") -> 5 | R9: =IFERROR(O9/B9,0) -> 0.61111111 | S9: =SUMIF('Detalle asesor'!$B$2:$B$264,$A9,'Detalle asesor'!$V$2:$V$264) -> 18955 | T9: =SUMIF('Detalle asesor'!$B$2:$B$264,$A9,'Detalle asesor'!$Y$2:$Y$264) -> 5722 | U9: =SUMIF('Detalle asesor'!$B$2:$B$264,$A9,'Detalle asesor'!$W$2:$W$264) -> 12941.5 | V9: =IFERROR(U9/S9,0) -> 0.68274862
A10: Counter | B10: =COUNTIF('Detalle asesor'!$B$2:$B$264,$A10) -> 34 | C10: =SUMIF('Detalle asesor'!$B$2:$B$264,$A10,'Detalle asesor'!$F$2:$F$264) -> 24.5 | D10: =SUMIF('Detalle asesor'!$B$2:$B$264,$A10,'Detalle asesor'!$G$2:$G$264) -> 342 | E10: =SUMIF('Detalle asesor'!$B$2:$B$264,$A10,'Detalle asesor'!$H$2:$H$264) -> 451 | F10: =IFERROR(D10/E10,0) -> 0.75831486 | G10: =SUMIF('Detalle asesor'!$B$2:$B$264,$A10,'Detalle asesor'!$J$2:$J$264) -> 44 | H10: =SUMIF('Detalle asesor'!$B$2:$B$264,$A10,'Detalle asesor'!$N$2:$N$264) -> 72.909091 | I10: =SUMIF('Detalle asesor'!$B$2:$B$264,$A10,'Detalle asesor'!$O$2:$O$264) -> 194 | J10: =IFERROR(H10/I10,0) -> 0.37582006 | K10: =Parametros!$B$3*F10+Parametros!$B$4*IFERROR(G10/I10,0) -> 0.59886164 | L10: =Parametros!$B$3*F10+Parametros!$B$4*J10 -> 0.64356642 | M10: =D10-E10 -> -109 | N10: =H10-I10 -> -121.09091 | O10: =COUNTIFS('Detalle asesor'!$B$2:$B$264,$A10,'Detalle asesor'!$Z$2:$Z$264,"Activa") -> 8 | P10: =COUNTIFS('Detalle asesor'!$B$2:$B$264,$A10,'Detalle asesor'!$Z$2:$Z$264,"Cerca") -> 2 | Q10: =COUNTIFS('Detalle asesor'!$B$2:$B$264,$A10,'Detalle asesor'!$Z$2:$Z$264,"No activa") -> 24 | R10: =IFERROR(O10/B10,0) -> 0.23529412 | S10: =SUMIF('Detalle asesor'!$B$2:$B$264,$A10,'Detalle asesor'!$V$2:$V$264) -> 30245 | T10: =SUMIF('Detalle asesor'!$B$2:$B$264,$A10,'Detalle asesor'!$Y$2:$Y$264) -> 12150 | U10: =SUMIF('Detalle asesor'!$B$2:$B$264,$A10,'Detalle asesor'!$W$2:$W$264) -> 13470 | V10: =IFERROR(U10/S10,0) -> 0.44536287
A11: Ate | B11: =COUNTIF('Detalle asesor'!$B$2:$B$264,$A11) -> 13 | C11: =SUMIF('Detalle asesor'!$B$2:$B$264,$A11,'Detalle asesor'!$F$2:$F$264) -> 12.25 | D11: =SUMIF('Detalle asesor'!$B$2:$B$264,$A11,'Detalle asesor'!$G$2:$G$264) -> 30 | E11: =SUMIF('Detalle asesor'!$B$2:$B$264,$A11,'Detalle asesor'!$H$2:$H$264) -> 70 | F11: =IFERROR(D11/E11,0) -> 0.42857143 | G11: =SUMIF('Detalle asesor'!$B$2:$B$264,$A11,'Detalle asesor'!$J$2:$J$264) -> 7 | H11: =SUMIF('Detalle asesor'!$B$2:$B$264,$A11,'Detalle asesor'!$N$2:$N$264) -> 12 | I11: =SUMIF('Detalle asesor'!$B$2:$B$264,$A11,'Detalle asesor'!$O$2:$O$264) -> 86 | J11: =IFERROR(H11/I11,0) -> 0.13953488 | K11: =Parametros!$B$3*F11+Parametros!$B$4*IFERROR(G11/I11,0) -> 0.3244186 | L11: =Parametros!$B$3*F11+Parametros!$B$4*J11 -> 0.34186047 | M11: =D11-E11 -> -40 | N11: =H11-I11 -> -74 | O11: =COUNTIFS('Detalle asesor'!$B$2:$B$264,$A11,'Detalle asesor'!$Z$2:$Z$264,"Activa") -> 2 | P11: =COUNTIFS('Detalle asesor'!$B$2:$B$264,$A11,'Detalle asesor'!$Z$2:$Z$264,"Cerca") -> 0 | Q11: =COUNTIFS('Detalle asesor'!$B$2:$B$264,$A11,'Detalle asesor'!$Z$2:$Z$264,"No activa") -> 11 | R11: =IFERROR(O11/B11,0) -> 0.15384615 | S11: =SUMIF('Detalle asesor'!$B$2:$B$264,$A11,'Detalle asesor'!$V$2:$V$264) -> 14700 | T11: =SUMIF('Detalle asesor'!$B$2:$B$264,$A11,'Detalle asesor'!$Y$2:$Y$264) -> 3600 | U11: =SUMIF('Detalle asesor'!$B$2:$B$264,$A11,'Detalle asesor'!$W$2:$W$264) -> 3600 | V11: =IFERROR(U11/S11,0) -> 0.24489796
A12: Lima Sur | B12: =COUNTIF('Detalle asesor'!$B$2:$B$264,$A12) -> 28 | C12: =SUMIF('Detalle asesor'!$B$2:$B$264,$A12,'Detalle asesor'!$F$2:$F$264) -> 0 | D12: =SUMIF('Detalle asesor'!$B$2:$B$264,$A12,'Detalle asesor'!$G$2:$G$264) -> 104 | E12: =SUMIF('Detalle asesor'!$B$2:$B$264,$A12,'Detalle asesor'!$H$2:$H$264) -> 160 | F12: =IFERROR(D12/E12,0) -> 0.65 | G12: =SUMIF('Detalle asesor'!$B$2:$B$264,$A12,'Detalle asesor'!$J$2:$J$264) -> 10 | H12: =SUMIF('Detalle asesor'!$B$2:$B$264,$A12,'Detalle asesor'!$N$2:$N$264) -> 19 | I12: =SUMIF('Detalle asesor'!$B$2:$B$264,$A12,'Detalle asesor'!$O$2:$O$264) -> 209 | J12: =IFERROR(H12/I12,0) -> 0.090909091 | K12: =Parametros!$B$3*F12+Parametros!$B$4*IFERROR(G12/I12,0) -> 0.46935407 | L12: =Parametros!$B$3*F12+Parametros!$B$4*J12 -> 0.48227273 | M12: =D12-E12 -> -56 | N12: =H12-I12 -> -190 | O12: =COUNTIFS('Detalle asesor'!$B$2:$B$264,$A12,'Detalle asesor'!$Z$2:$Z$264,"Activa") -> 6 | P12: =COUNTIFS('Detalle asesor'!$B$2:$B$264,$A12,'Detalle asesor'!$Z$2:$Z$264,"Cerca") -> 4 | Q12: =COUNTIFS('Detalle asesor'!$B$2:$B$264,$A12,'Detalle asesor'!$Z$2:$Z$264,"No activa") -> 18 | R12: =IFERROR(O12/B12,0) -> 0.21428571 | S12: =SUMIF('Detalle asesor'!$B$2:$B$264,$A12,'Detalle asesor'!$V$2:$V$264) -> 0 | T12: =SUMIF('Detalle asesor'!$B$2:$B$264,$A12,'Detalle asesor'!$Y$2:$Y$264) -> 0 | U12: =SUMIF('Detalle asesor'!$B$2:$B$264,$A12,'Detalle asesor'!$W$2:$W$264) -> 0 | V12: =IFERROR(U12/S12,0) -> 0
A13: ReiNew | B13: =COUNTIF('Detalle asesor'!$B$2:$B$264,$A13) -> 20 | C13: =SUMIF('Detalle asesor'!$B$2:$B$264,$A13,'Detalle asesor'!$F$2:$F$264) -> 18.318182 | D13: =SUMIF('Detalle asesor'!$B$2:$B$264,$A13,'Detalle asesor'!$G$2:$G$264) -> 48 | E13: =SUMIF('Detalle asesor'!$B$2:$B$264,$A13,'Detalle asesor'!$H$2:$H$264) -> 380 | F13: =IFERROR(D13/E13,0) -> 0.12631579 | G13: =SUMIF('Detalle asesor'!$B$2:$B$264,$A13,'Detalle asesor'!$J$2:$J$264) -> 0 | H13: =SUMIF('Detalle asesor'!$B$2:$B$264,$A13,'Detalle asesor'!$N$2:$N$264) -> 0 | I13: =SUMIF('Detalle asesor'!$B$2:$B$264,$A13,'Detalle asesor'!$O$2:$O$264) -> 184 | J13: =IFERROR(H13/I13,0) -> 0 | K13: =Parametros!$B$3*F13+Parametros!$B$4*IFERROR(G13/I13,0) -> 0.088421053 | L13: =Parametros!$B$3*F13+Parametros!$B$4*J13 -> 0.088421053 | M13: =D13-E13 -> -332 | N13: =H13-I13 -> -184 | O13: =COUNTIFS('Detalle asesor'!$B$2:$B$264,$A13,'Detalle asesor'!$Z$2:$Z$264,"Activa") -> 0 | P13: =COUNTIFS('Detalle asesor'!$B$2:$B$264,$A13,'Detalle asesor'!$Z$2:$Z$264,"Cerca") -> 0 | Q13: =COUNTIFS('Detalle asesor'!$B$2:$B$264,$A13,'Detalle asesor'!$Z$2:$Z$264,"No activa") -> 20 | R13: =IFERROR(O13/B13,0) -> 0 | S13: =SUMIF('Detalle asesor'!$B$2:$B$264,$A13,'Detalle asesor'!$V$2:$V$264) -> 21981 | T13: =SUMIF('Detalle asesor'!$B$2:$B$264,$A13,'Detalle asesor'!$Y$2:$Y$264) -> 0 | U13: =SUMIF('Detalle asesor'!$B$2:$B$264,$A13,'Detalle asesor'!$W$2:$W$264) -> 0 | V13: =IFERROR(U13/S13,0) -> 0
A14: TOTAL | B14: =SUM(B5:B13) -> 263 | C14: =SUM(C5:C13) -> 204.72727 | D14: =SUM(D5:D13) -> 1270 | E14: =SUM(E5:E13) -> 2793 | F14: =IFERROR(D14/E14,0) -> 0.4547082 | G14: =SUM(G5:G13) -> 593 | H14: =SUM(H5:H13) -> 1015.0273 | I14: =SUM(I5:I13) -> 1334 | J14: =IFERROR(H14/I14,0) -> 0.76089001 | K14: =Parametros!$B$3*F14+Parametros!$B$4*IFERROR(G14/I14,0) -> 0.45165406 | L14: =Parametros!$B$3*F14+Parametros!$B$4*J14 -> 0.54656274 | M14: =SUM(M5:M13) -> -1523 | N14: =SUM(N5:N13) -> -318.97273 | O14: =SUM(O5:O13) -> 76 | P14: =SUM(P5:P13) -> 14 | Q14: =SUM(Q5:Q13) -> 173 | R14: =IFERROR(O14/B14,0) -> 0.28897338 | S14: =SUM(S5:S13) -> 248917 | T14: =SUM(T5:T13) -> 49192 | U14: =SUM(U5:U13) -> 95986.5 | V14: =IFERROR(U14/S14,0) -> 0.38561649
A16: Check: la dotación total debe igualar las filas de la base (263). | F16: =IF(B14=COUNTA(base!$A$2:$A$264),"OK","Revisar") -> OK

Sheet Detalle asesor
A1: Código PS | B1: Pool | C1: Pool equivalente | D1: Líder grupo | E1: Jefe inmediato | F1: HC | G1: Venta PM | H1: Meta PM | I1: % PM | J1: CM real cargado | K1: Ritmo CM / sem activa | L1: CM S39 proy | M1: CM S40 proy | N1: CM proyectado | O1: Meta CM | P1: % CM real | Q1: % CM proy | R1: Cumpl. actual | S1: Cumpl. proyectado | T1: Nivel proyectado | U1: Acelerador proy | V1: Carta (S/) | W1: Gasto proyectado (S/) | X1: Nivel actual | Y1: Gasto actual (S/) | Z1: Estado | AA1: Falta a 80% (pts)
A2: =base!A2 -> 46050977-2 | B2: =base!E2 -> Counter | C2: =base!D2 -> Counter | D2: =base!F2 -> ARACELI TARAZONA SERNAQUE | E2: =base!G2 -> GISELA AVELLANEDA CAMACHO | F2: =N(base!O2) -> 1 | G2: =SUM(base!U2:AF2)+N(base!AK2) -> 7 | H2: =N(base!S2) -> 21 | I2: =IFERROR(G2/H2,0) -> 0.33333333 | J2: =SUM(base!AG2:AJ2) -> 0 | K2: =IFERROR((base!AG2+base!AH2)/(base!K2+base!L2),0) -> 0 | L2: =MAX(N(base!AI2),K2*N(base!M2)) -> 0 | M2: =MAX(N(base!AJ2),K2*N(base!N2)) -> 0 | N2: =base!AG2+base!AH2+L2+M2 -> 0 | O2: =N(base!T2) -> 9 | P2: =IFERROR(J2/O2,0) -> 0 | Q2: =IFERROR(N2/O2,0) -> 0 | R2: =Parametros!$B$3*I2+Parametros!$B$4*P2 -> 0.23333333 | S2: =Parametros!$B$3*I2+Parametros!$B$4*Q2 -> 0.23333333 | T2: =IF(S2<tablas!$C$3,"No activa",INDEX(tablas!$B$3:$B$8,MATCH(S2,tablas!$C$3:$C$8,1))) -> No activa | U2: =IF(S2<tablas!$C$3,0,INDEX(tablas!$D$3:$D$8,MATCH(S2,tablas!$C$3:$C$8,1))) -> 0 | V2: =N(base!AQ2) -> 1200 | W2: =U2*V2 -> 0 | X2: =IF(R2<tablas!$C$3,"No activa",INDEX(tablas!$B$3:$B$8,MATCH(R2,tablas!$C$3:$C$8,1))) -> No activa | Y2: =IF(R2<tablas!$C$3,0,INDEX(tablas!$D$3:$D$8,MATCH(R2,tablas!$C$3:$C$8,1)))*V2 -> 0 | Z2: =IF(S2>=tablas!$C$3,"Activa",IF(S2>=Parametros!$B$5,"Cerca","No activa")) -> No activa | AA2: =MAX(0,tablas!$C$3-S2) -> 0.56666667
A3: =base!A3 -> 77078190-1 | B3: =base!E3 -> Counter | C3: =base!D3 -> Counter | D3: =base!F3 -> ARACELI TARAZONA SERNAQUE | E3: =base!G3 -> GISELA AVELLANEDA CAMACHO | F3: =N(base!O3) -> 1 | G3: =SUM(base!U3:AF3)+N(base!AK3) -> 9 | H3: =N(base!S3) -> 21 | I3: =IFERROR(G3/H3,0) -> 0.42857143 | J3: =SUM(base!AG3:AJ3) -> 0 | K3: =IFERROR((base!AG3+base!AH3)/(base!K3+base!L3),0) -> 0 | L3: =MAX(N(base!AI3),K3*N(base!M3)) -> 0 | M3: =MAX(N(base!AJ3),K3*N(base!N3)) -> 0 | N3: =base!AG3+base!AH3+L3+M3 -> 0 | O3: =N(base!T3) -> 9 | P3: =IFERROR(J3/O3,0) -> 0 | Q3: =IFERROR(N3/O3,0) -> 0 | R3: =Parametros!$B$3*I3+Parametros!$B$4*P3 -> 0.3 | S3: =Parametros!$B$3*I3+Parametros!$B$4*Q3 -> 0.3 | T3: =IF(S3<tablas!$C$3,"No activa",INDEX(tablas!$B$3:$B$8,MATCH(S3,tablas!$C$3:$C$8,1))) -> No activa | U3: =IF(S3<tablas!$C$3,0,INDEX(tablas!$D$3:$D$8,MATCH(S3,tablas!$C$3:$C$8,1))) -> 0 | V3: =N(base!AQ3) -> 1200 | W3: =U3*V3 -> 0 | X3: =IF(R3<tablas!$C$3,"No activa",INDEX(tablas!$B$3:$B$8,MATCH(R3,tablas!$C$3:$C$8,1))) -> No activa | Y3: =IF(R3<tablas!$C$3,0,INDEX(tablas!$D$3:$D$8,MATCH(R3,tablas!$C$3:$C$8,1)))*V3 -> 0 | Z3: =IF(S3>=tablas!$C$3,"Activa",IF(S3>=Parametros!$B$5,"Cerca","No activa")) -> No activa | AA3: =MAX(0,tablas!$C$3-S3) -> 0.5
A4: =base!A4 -> 47567126-6 | B4: =base!E4 -> Counter | C4: =base!D4 -> Counter | D4: =base!F4 -> ARACELI TARAZONA SERNAQUE | E4: =base!G4 -> GISELA AVELLANEDA CAMACHO | F4: =N(base!O4) -> 0.5 | G4: =SUM(base!U4:AF4)+N(base!AK4) -> 0 | H4: =N(base!S4) -> 8 | I4: =IFERROR(G4/H4,0) -> 0 | J4: =SUM(base!AG4:AJ4) -> 0 | K4: =IFERROR((base!AG4+base!AH4)/(base!K4+base!L4),0) -> 0 | L4: =MAX(N(base!AI4),K4*N(base!M4)) -> 0 | M4: =MAX(N(base!AJ4),K4*N(base!N4)) -> 0 | N4: =base!AG4+base!AH4+L4+M4 -> 0 | O4: =N(base!T4) -> 4 | P4: =IFERROR(J4/O4,0) -> 0 | Q4: =IFERROR(N4/O4,0) -> 0 | R4: =Parametros!$B$3*I4+Parametros!$B$4*P4 -> 0 | S4: =Parametros!$B$3*I4+Parametros!$B$4*Q4 -> 0 | T4: =IF(S4<tablas!$C$3,"No activa",INDEX(tablas!$B$3:$B$8,MATCH(S4,tablas!$C$3:$C$8,1))) -> No activa | U4: =IF(S4<tablas!$C$3,0,INDEX(tablas!$D$3:$D$8,MATCH(S4,tablas!$C$3:$C$8,1))) -> 0 | V4: =N(base!AQ4) -> 600 | W4: =U4*V4 -> 0 | X4: =IF(R4<tablas!$C$3,"No activa",INDEX(tablas!$B$3:$B$8,MATCH(R4,tablas!$C$3:$C$8,1))) -> No activa | Y4: =IF(R4<tablas!$C$3,0,INDEX(tablas!$D$3:$D$8,MATCH(R4,tablas!$C$3:$C$8,1)))*V4 -> 0 | Z4: =IF(S4>=tablas!$C$3,"Activa",IF(S4>=Parametros!$B$5,"Cerca","No activa")) -> No activa | AA4: =MAX(0,tablas!$C$3-S4) -> 0.8
A5: =base!A5 -> 41710085-2 | B5: =base!E5 -> Counter | C5: =base!D5 -> Counter | D5: =base!F5 -> ARACELI TARAZONA SERNAQUE | E5: =base!G5 -> GISELA AVELLANEDA CAMACHO | F5: =N(base!O5) -> 0.54545455 | G5: =SUM(base!U5:AF5)+N(base!AK5) -> 2 | H5: =N(base!S5) -> 11 | I5: =IFERROR(G5/H5,0) -> 0.18181818 | J5: =SUM(base!AG5:AJ5) -> 3 | K5: =IFERROR((base!AG5+base!AH5)/(base!K5+base!L5),0) -> 1.5 | L5: =MAX(N(base!AI5),K5*N(base!M5)) -> 0.27272727 | M5: =MAX(N(base!AJ5),K5*N(base!N5)) -> 0 | N5: =base!AG5+base!AH5+L5+M5 -> 3.2727273 | O5: =N(base!T5) -> 5 | P5: =IFERROR(J5/O5,0) -> 0.6 | Q5: =IFERROR(N5/O5,0) -> 0.65454545 | R5: =Parametros!$B$3*I5+Parametros!$B$4*P5 -> 0.30727273 | S5: =Parametros!$B$3*I5+Parametros!$B$4*Q5 -> 0.32363636 | T5: =IF(S5<tablas!$C$3,"No activa",INDEX(tablas!$B$3:$B$8,MATCH(S5,tablas!$C$3:$C$8,1))) -> No activa | U5: =IF(S5<tablas!$C$3,0,INDEX(tablas!$D$3:$D$8,MATCH(S5,tablas!$C$3:$C$8,1))) -> 0 | V5: =N(base!AQ5) -> 655 | W5: =U5*V5 -> 0 | X5: =IF(R5<tablas!$C$3,"No activa",INDEX(tablas!$B$3:$B$8,MATCH(R5,tablas!$C$3:$C$8,1))) -> No activa | Y5: =IF(R5<tablas!$C$3,0,INDEX(tablas!$D$3:$D$8,MATCH(R5,tablas!$C$3:$C$8,1)))*V5 -> 0 | Z5: =IF(S5>=tablas!$C$3,"Activa",IF(S5>=Parametros!$B$5,"Cerca","No activa")) -> No activa | AA5: =MAX(0,tablas!$C$3-S5) -> 0.47636364
A6: =base!A6 -> 42763046-9 | B6: =base!E6 -> Counter | C6: =base!D6 -> Counter | D6: =base!F6 -> ARACELI TARAZONA SERNAQUE | E6: =base!G6 -> GISELA AVELLANEDA CAMACHO | F6: =N(base!O6) -> 1 | G6: =SUM(base!U6:AF6)+N(base!AK6) -> 12 | H6: =N(base!S6) -> 21 | I6: =IFERROR(G6/H6,0) -> 0.57142857 | J6: =SUM(base!AG6:AJ6) -> 2 | K6: =IFERROR((base!AG6+base!AH6)/(base!K6+base!L6),0) -> 1 | L6: =MAX(N(base!AI6),K6*N(base!M6)) -> 1 | M6: =MAX(N(base!AJ6),K6*N(base!N6)) -> 1 | N6: =base!AG6+base!AH6+L6+M6 -> 4 | O6: =N(base!T6) -> 8 | P6: =IFERROR(J6/O6,0) -> 0.25 | Q6: =IFERROR(N6/O6,0) -> 0.5 | R6: =Parametros!$B$3*I6+Parametros!$B$4*P6 -> 0.475 | S6: =Parametros!$B$3*I6+Parametros!$B$4*Q6 -> 0.55 | T6: =IF(S6<tablas!$C$3,"No activa",INDEX(tablas!$B$3:$B$8,MATCH(S6,tablas!$C$3:$C$8,1))) -> No activa | U6: =IF(S6<tablas!$C$3,0,INDEX(tablas!$D$3:$D$8,MATCH(S6,tablas!$C$3:$C$8,1))) -> 0 | V6: =N(base!AQ6) -> 1200 | W6: =U6*V6 -> 0 | X6: =IF(R6<tablas!$C$3,"No activa",INDEX(tablas!$B$3:$B$8,MATCH(R6,tablas!$C$3:$C$8,1))) -> No activa | Y6: =IF(R6<tablas!$C$3,0,INDEX(tablas!$D$3:$D$8,MATCH(R6,tablas!$C$3:$C$8,1)))*V6 -> 0 | Z6: =IF(S6>=tablas!$C$3,"Activa",IF(S6>=Parametros!$B$5,"Cerca","No activa")) -> No activa | AA6: =MAX(0,tablas!$C$3-S6) -> 0.25
A7: =base!A7 -> 41907916-8 | B7: =base!E7 -> Counter | C7: =base!D7 -> Counter | D7: =base!F7 -> ARACELI TARAZONA SERNAQUE | E7: =base!G7 -> GISELA AVELLANEDA CAMACHO | F7: =N(base!O7) -> 1 | G7: =SUM(base!U7:AF7)+N(base!AK7) -> 0 | H7: =N(base!S7) -> 15 | I7: =IFERROR(G7/H7,0) -> 0 | J7: =SUM(base!AG7:AJ7) -> 1 | K7: =IFERROR((base!AG7+base!AH7)/(base!K7+base!L7),0) -> 0.5 | L7: =MAX(N(base!AI7),K7*N(base!M7)) -> 0.5 | M7: =MAX(N(base!AJ7),K7*N(base!N7)) -> 0.5 | N7: =base!AG7+base!AH7+L7+M7 -> 2 | O7: =N(base!T7) -> 6 | P7: =IFERROR(J7/O7,0) -> 0.16666667 | Q7: =IFERROR(N7/O7,0) -> 0.33333333 | R7: =Parametros!$B$3*I7+Parametros!$B$4*P7 -> 0.05 | S7: =Parametros!$B$3*I7+Parametros!$B$4*Q7 -> 0.1 | T7: =IF(S7<tablas!$C$3,"No activa",INDEX(tablas!$B$3:$B$8,MATCH(S7,tablas!$C$3:$C$8,1))) -> No activa | U7: =IF(S7<tablas!$C$3,0,INDEX(tablas!$D$3:$D$8,MATCH(S7,tablas!$C$3:$C$8,1))) -> 0 | V7: =N(base!AQ7) -> 1200 | W7: =U7*V7 -> 0 | X7: =IF(R7<tablas!$C$3,"No activa",INDEX(tablas!$B$3:$B$8,MATCH(R7,tablas!$C$3:$C$8,1))) -> No activa | Y7: =IF(R7<tablas!$C$3,0,INDEX(tablas!$D$3:$D$8,MATCH(R7,tablas!$C$3:$C$8,1)))*V7 -> 0 | Z7: =IF(S7>=tablas!$C$3,"Activa",IF(S7>=Parametros!$B$5,"Cerca","No activa")) -> No activa | AA7: =MAX(0,tablas!$C$3-S7) -> 0.7
A8: =base!A8 -> 46569779-8 | B8: =base!E8 -> Counter | C8: =base!D8 -> Counter | D8: =base!F8 -> ARACELI TARAZONA SERNAQUE | E8: =base!G8 -> GISELA AVELLANEDA CAMACHO | F8: =N(base!O8) -> 0.45454545 | G8: =SUM(base!U8:AF8)+N(base!AK8) -> 0 | H8: =N(base!S8) -> 10 | I8: =IFERROR(G8/H8,0) -> 0 | J8: =SUM(base!AG8:AJ8) -> 0 | K8: =IFERROR((base!AG8+base!AH8)/(base!K8+base!L8),0) -> 0 | L8: =MAX(N(base!AI8),K8*N(base!M8)) -> 0 | M8: =MAX(N(base!AJ8),K8*N(base!N8)) -> 0 | N8: =base!AG8+base!AH8+L8+M8 -> 0 | O8: =N(base!T8) -> 3 | P8: =IFERROR(J8/O8,0) -> 0 | Q8: =IFERROR(N8/O8,0) -> 0 | R8: =Parametros!$B$3*I8+Parametros!$B$4*P8 -> 0 | S8: =Parametros!$B$3*I8+Parametros!$B$4*Q8 -> 0 | T8: =IF(S8<tablas!$C$3,"No activa",INDEX(tablas!$B$3:$B$8,MATCH(S8,tablas!$C$3:$C$8,1))) -> No activa | U8: =IF(S8<tablas!$C$3,0,INDEX(tablas!$D$3:$D$8,MATCH(S8,tablas!$C$3:$C$8,1))) -> 0 | V8: =N(base!AQ8) -> 545 | W8: =U8*V8 -> 0 | X8: =IF(R8<tablas!$C$3,"No activa",INDEX(tablas!$B$3:$B$8,MATCH(R8,tablas!$C$3:$C$8,1))) -> No activa | Y8: =IF(R8<tablas!$C$3,0,INDEX(tablas!$D$3:$D$8,MATCH(R8,tablas!$C$3:$C$8,1)))*V8 -> 0 | Z8: =IF(S8>=tablas!$C$3,"Activa",IF(S8>=Parametros!$B$5,"Cerca","No activa")) -> No activa | AA8: =MAX(0,tablas!$C$3-S8) -> 0.8
A9: =base!A9 -> 46349775-9 | B9: =base!E9 -> Counter | C9: =base!D9 -> Counter | D9: =base!F9 -> ARACELI TARAZONA SERNAQUE | E9: =base!G9 -> GISELA AVELLANEDA CAMACHO | F9: =N(base!O9) -> 0.5 | G9: =SUM(base!U9:AF9)+N(base!AK9) -> 5 | H9: =N(base!S9) -> 8 | I9: =IFERROR(G9/H9,0) -> 0.625 | J9: =SUM(base!AG9:AJ9) -> 0 | K9: =IFERROR((base!AG9+base!AH9)/(base!K9+base!L9),0) -> 0 | L9: =MAX(N(base!AI9),K9*N(base!M9)) -> 0 | M9: =MAX(N(base!AJ9),K9*N(base!N9)) -> 0 | N9: =base!AG9+base!AH9+L9+M9 -> 0 | O9: =N(base!T9) -> 3 | P9: =IFERROR(J9/O9,0) -> 0 | Q9: =IFERROR(N9/O9,0) -> 0 | R9: =Parametros!$B$3*I9+Parametros!$B$4*P9 -> 0.4375 | S9: =Parametros!$B$3*I9+Parametros!$B$4*Q9 -> 0.4375 | T9: =IF(S9<tablas!$C$3,"No activa",INDEX(tablas!$B$3:$B$8,MATCH(S9,tablas!$C$3:$C$8,1))) -> No activa | U9: =IF(S9<tablas!$C$3,0,INDEX(tablas!$D$3:$D$8,MATCH(S9,tablas!$C$3:$C$8,1))) -> 0 | V9: =N(base!AQ9) -> 600 | W9: =U9*V9 -> 0 | X9: =IF(R9<tablas!$C$3,"No activa",INDEX(tablas!$B$3:$B$8,MATCH(R9,tablas!$C$3:$C$8,1))) -> No activa | Y9: =IF(R9<tablas!$C$3,0,INDEX(tablas!$D$3:$D$8,MATCH(R9,tablas!$C$3:$C$8,1)))*V9 -> 0 | Z9: =IF(S9>=tablas!$C$3,"Activa",IF(S9>=Parametros!$B$5,"Cerca","No activa")) -> No activa | AA9: =MAX(0,tablas!$C$3-S9) -> 0.3625
A10: =base!A10 -> 25831501-0 | B10: =base!E10 -> Counter | C10: =base!D10 -> Counter | D10: =base!F10 -> JENNY ALEJANDRA DE LA CRUZ FLORES | E10: =base!G10 -> GISELA AVELLANEDA CAMACHO | F10: =N(base!O10) -> 0.45454545 | G10: =SUM(base!U10:AF10)+N(base!AK10) -> 0 | H10: =N(base!S10) -> 10 | I10: =IFERROR(G10/H10,0) -> 0 | J10: =SUM(base!AG10:AJ10) -> 0 | K10: =IFERROR((base!AG10+base!AH10)/(base!K10+base!L10),0) -> 0 | L10: =MAX(N(base!AI10),K10*N(base!M10)) -> 0 | M10: =MAX(N(base!AJ10),K10*N(base!N10)) -> 0 | N10: =base!AG10+base!AH10+L10+M10 -> 0 | O10: =N(base!T10) -> 4 | P10: =IFERROR(J10/O10,0) -> 0 | Q10: =IFERROR(N10/O10,0) -> 0 | R10: =Parametros!$B$3*I10+Parametros!$B$4*P10 -> 0 | S10: =Parametros!$B$3*I10+Parametros!$B$4*Q10 -> 0 | T10: =IF(S10<tablas!$C$3,"No activa",INDEX(tablas!$B$3:$B$8,MATCH(S10,tablas!$C$3:$C$8,1))) -> No activa | U10: =IF(S10<tablas!$C$3,0,INDEX(tablas!$D$3:$D$8,MATCH(S10,tablas!$C$3:$C$8,1))) -> 0 | V10: =N(base!AQ10) -> 545 | W10: =U10*V10 -> 0 | X10: =IF(R10<tablas!$C$3,"No activa",INDEX(tablas!$B$3:$B$8,MATCH(R10,tablas!$C$3:$C$8,1))) -> No activa | Y10: =IF(R10<tablas!$C$3,0,INDEX(tablas!$D$3:$D$8,MATCH(R10,tablas!$C$3:$C$8,1)))*V10 -> 0 | Z10: =IF(S10>=tablas!$C$3,"Activa",IF(S10>=Parametros!$B$5,"Cerca","No activa")) -> No activa | AA10: =MAX(0,tablas!$C$3-S10) -> 0.8
A11: =base!A11 -> 45172927-1 | B11: =base!E11 -> Counter | C11: =base!D11 -> Counter | D11: =base!F11 -> JENNY ALEJANDRA DE LA CRUZ FLORES | E11: =base!G11 -> GISELA AVELLANEDA CAMACHO | F11: =N(base!O11) -> 1 | G11: =SUM(base!U11:AF11)+N(base!AK11) -> 3 | H11: =N(base!S11) -> 17 | I11: =IFERROR(G11/H11,0) -> 0.17647059 | J11: =SUM(base!AG11:AJ11) -> 2 | K11: =IFERROR((base!AG11+base!AH11)/(base!K11+base!L11),0) -> 1 | L11: =MAX(N(base!AI11),K11*N(base!M11)) -> 1 | M11: =MAX(N(base!AJ11),K11*N(base!N11)) -> 1 | N11: =base!AG11+base!AH11+L11+M11 -> 4 | O11: =N(base!T11) -> 5 | P11: =IFERROR(J11/O11,0) -> 0.4 | Q11: =IFERROR(N11/O11,0) -> 0.8 | R11: =Parametros!$B$3*I11+Parametros!$B$4*P11 -> 0.24352941 | S11: =Parametros!$B$3*I11+Parametros!$B$4*Q11 -> 0.36352941 | T11: =IF(S11<tablas!$C$3,"No activa",INDEX(tablas!$B$3:$B$8,MATCH(S11,tablas!$C$3:$C$8,1))) -> No activa | U11: =IF(S11<tablas!$C$3,0,INDEX(tablas!$D$3:$D$8,MATCH(S11,tablas!$C$3:$C$8,1))) -> 0 | V11: =N(base!AQ11) -> 1200 | W11: =U11*V11 -> 0 | X11: =IF(R11<tablas!$C$3,"No activa",INDEX(tablas!$B$3:$B$8,MATCH(R11,tablas!$C$3:$C$8,1))) -> No activa | Y11: =IF(R11<tablas!$C$3,0,INDEX(tablas!$D$3:$D$8,MATCH(R11,tablas!$C$3:$C$8,1)))*V11 -> 0 | Z11: =IF(S11>=tablas!$C$3,"Activa",IF(S11>=Parametros!$B$5,"Cerca","No activa")) -> No activa | AA11: =MAX(0,tablas!$C$3-S11) -> 0.43647059
A12: =base!A12 -> 70862248-1 | B12: =base!E12 -> Counter | C12: =base!D12 -> Counter | D12: =base!F12 -> JENNY ALEJANDRA DE LA CRUZ FLORES | E12: =base!G12 -> GISELA AVELLANEDA CAMACHO | F12: =N(base!O12) -> 0.54545455 | G12: =SUM(base!U12:AF12)+N(base!AK12) -> 4 | H12: =N(base!S12) -> 12 | I12: =IFERROR(G12/H12,0) -> 0.33333333 | J12: =SUM(base!AG12:AJ12) -> 5 | K12: =IFERROR((base!AG12+base!AH12)/(base!K12+base!L12),0) -> 2.5 | L12: =MAX(N(base!AI12),K12*N(base!M12)) -> 0.45454545 | M12: =MAX(N(base!AJ12),K12*N(base!N12)) -> 0 | N12: =base!AG12+base!AH12+L12+M12 -> 5.4545455 | O12: =N(base!T12) -> 3 | P12: =IFERROR(J12/O12,0) -> 1.6666667 | Q12: =IFERROR(N12/O12,0) -> 1.8181818 | R12: =Parametros!$B$3*I12+Parametros!$B$4*P12 -> 0.73333333 | S12: =Parametros!$B$3*I12+Parametros!$B$4*Q12 -> 0.77878788 | T12: =IF(S12<tablas!$C$3,"No activa",INDEX(tablas!$B$3:$B$8,MATCH(S12,tablas!$C$3:$C$8,1))) -> No activa | U12: =IF(S12<tablas!$C$3,0,INDEX(tablas!$D$3:$D$8,MATCH(S12,tablas!$C$3:$C$8,1))) -> 0 | V12: =N(base!AQ12) -> 655 | W12: =U12*V12 -> 0 | X12: =IF(R12<tablas!$C$3,"No activa",INDEX(tablas!$B$3:$B$8,MATCH(R12,tablas!$C$3:$C$8,1))) -> No activa | Y12: =IF(R12<tablas!$C$3,0,INDEX(tablas!$D$3:$D$8,MATCH(R12,tablas!$C$3:$C$8,1)))*V12 -> 0 | Z12: =IF(S12>=tablas!$C$3,"Activa",IF(S12>=Parametros!$B$5,"Cerca","No activa")) -> Cerca | AA12: =MAX(0,tablas!$C$3-S12) -> 0.021212121
A13: =base!A13 -> 46824537-5 | B13: =base!E13 -> Counter | C13: =base!D13 -> Counter | D13: =base!F13 -> JENNY ALEJANDRA DE LA CRUZ FLORES | E13: =base!G13 -> GISELA AVELLANEDA CAMACHO | F13: =N(base!O13) -> 0.54545455 | G13: =SUM(base!U13:AF13)+N(base!AK13) -> 0 | H13: =N(base!S13) -> 9 | I13: =IFERROR(G13/H13,0) -> 0 | J13: =SUM(base!AG13:AJ13) -> 2 | K13: =IFERROR((base!AG13+base!AH13)/(base!K13+base!L13),0) -> 1 | L13: =MAX(N(base!AI13),K13*N(base!M13)) -> 0.18181818 | M13: =MAX(N(base!AJ13),K13*N(base!N13)) -> 0 | N13: =base!AG13+base!AH13+L13+M13 -> 2.1818182 | O13: =N(base!T13) -> 4 | P13: =IFERROR(J13/O13,0) -> 0.5 | Q13: =IFERROR(N13/O13,0) -> 0.54545455 | R13: =Parametros!$B$3*I13+Parametros!$B$4*P13 -> 0.15 | S13: =Parametros!$B$3*I13+Parametros!$B$4*Q13 -> 0.16363636 | T13: =IF(S13<tablas!$C$3,"No activa",INDEX(tablas!$B$3:$B$8,MATCH(S13,tablas!$C$3:$C$8,1))) -> No activa | U13: =IF(S13<tablas!$C$3,0,INDEX(tablas!$D$3:$D$8,MATCH(S13,tablas!$C$3:$C$8,1))) -> 0 | V13: =N(base!AQ13) -> 655 | W13: =U13*V13 -> 0 | X13: =IF(R13<tablas!$C$3,"No activa",INDEX(tablas!$B$3:$B$8,MATCH(R13,tablas!$C$3:$C$8,1))) -> No activa | Y13: =IF(R13<tablas!$C$3,0,INDEX(tablas!$D$3:$D$8,MATCH(R13,tablas!$C$3:$C$8,1)))*V13 -> 0 | Z13: =IF(S13>=tablas!$C$3,"Activa",IF(S13>=Parametros!$B$5,"Cerca","No activa")) -> No activa | AA13: =MAX(0,tablas!$C$3-S13) -> 0.63636364
... A264: =base!A264 -> 48768139-9 | B264: =base!E264 -> Lima Sur | C264: =base!D264 -> Outbound | D264: =base!F264 -> MARITZA HUAMAN NAVARRO | E264: =base!G264 -> JOSUE MORA SOLSOL | F264: =N(base!O264) -> 0 | G264: =SUM(base!U264:AF264)+N(base!AK264) -> 0 | H264: =N(base!S264) -> 3 | I264: =IFERROR(G264/H264,0) -> 0 | J264: =SUM(base!AG264:AJ264) -> 0 | K264: =IFERROR((base!AG264+base!AH264)/(base!K264+base!L264),0) -> 0 | L264: =MAX(N(base!AI264),K264*N(base!M264)) -> 0 | M264: =MAX(N(base!AJ264),K264*N(base!N264)) -> 0 | N264: =base!AG264+base!AH264+L264+M264 -> 0 | O264: =N(base!T264) -> 2 | P264: =IFERROR(J264/O264,0) -> 0 | Q264: =IFERROR(N264/O264,0) -> 0 | R264: =Parametros!$B$3*I264+Parametros!$B$4*P264 -> 0 | S264: =Parametros!$B$3*I264+Parametros!$B$4*Q264 -> 0 | T264: =IF(S264<tablas!$C$3,"No activa",INDEX(tablas!$B$3:$B$8,MATCH(S264,tablas!$C$3:$C$8,1))) -> No activa | U264: =IF(S264<tablas!$C$3,0,INDEX(tablas!$D$3:$D$8,MATCH(S264,tablas!$C$3:$C$8,1))) -> 0 | V264: =N(base!AQ264) -> 0 | W264: =U264*V264 -> 0 | X264: =IF(R264<tablas!$C$3,"No activa",INDEX(tablas!$B$3:$B$8,MATCH(R264,tablas!$C$3:$C$8,1))) -> No activa | Y264: =IF(R264<tablas!$C$3,0,INDEX(tablas!$D$3:$D$8,MATCH(R264,tablas!$C$3:$C$8,1)))*V264 -> 0 | Z264: =IF(S264>=tablas!$C$3,"Activa",IF(S264>=Parametros!$B$5,"Cerca","No activa")) -> No activa | AA264: =MAX(0,tablas!$C$3-S264) -> 0.8

Sheet Parametros
A1: Parámetros del modelo de proyección
A3: Peso PM (UG+WA+CAD+RN) | B3: 0.7 | C3: Dato del usuario (columna PESO PM de la base)
A4: Peso CM (MOD B) | B4: 0.3 | C4: Dato del usuario (columna PESO CM de la base)
A5: Umbral "cerca de activar" | B5: 0.7 | C5: Supuesto: asesores entre 70% y 80% se muestran como recuperables
A8: Supuestos de la proyección:
A9: 1. El periodo medido es S37–S40 (las columnas de vacaciones y el HC de la base cubren esas 4 semanas).
A10: 2. UG, WA, CAD y RN se consideran cerrados a S40 (con dato cargado en las 4 semanas).
A11: 3. MOD B (CM) solo tiene carga completa en S37–S38; S39 es parcial y S40 no tiene dato.
A12: Se proyecta con el ritmo de S37–S38 por semana activa × disponibilidad (Vac S39, Vac S40). Si el dato real es mayor, se usa el real.
A13: 4. Cumplimiento = Peso PM × %PM + Peso CM × %CM. Nivel y acelerador según hoja "tablas" (menos de 80% = No activa).
A14: 5. Gasto = CARTA (target prorrateado por % cuota) × acelerador.
A15: 6. La columna TOTAL VENTA de la base no cuadra con el detalle semanal; se recalcula desde el detalle.
A16: 7. Lima Sur no tiene TARGET ni % cuota cargado: su gasto sale en 0. ReiNew no tiene ventas MOD B: su %CM sale en 0.

Sheet base
A1: Código PS | B1: fecha ingreso | C1: Antigüedad | D1: POOL Equivalente | E1: POOL | F1: LIDER GRUPO | G1: Jefe Inmediato | H1: Sede | I1: Sede ST | J1: Dias Activos | K1: Vac S37 | L1: Vac S38 | M1: Vac S39 | N1: Vac S40 | O1: HC | P1: % cuota | Q1: Meta PM 2027.1 | R1: META MOD B CAD | S1: META PM TOTAL | T1: META CM | U1: UG S37 | V1: UG S38 | W1: UG S39 | X1: UG S40 | Y1: WA S37 | Z1: WA S38 | AA1: WA S39 | AB1: WA S40 | AC1: CAD S37 | AD1: CAD S38 | AE1: CAD S39 | AF1: CAD S40 | AG1: MOD B S37 | AH1: MOD B S38 | AI1: MOD B S39 | AJ1: MOD B S40 | AK1: RN | AL1: TOTAL VENTA | AM1: PESO PM | AN1: PESO CM | AO1: COMISION % | AP1: TARGET | AQ1: CARTA
A2: 46050977-2 | B2: 45139 | C2: VET | D2: Counter | E2: Counter | F2: ARACELI TARAZONA SERNAQUE | G2: GISELA AVELLANEDA CAMACHO | H2: LIMA OLIVOS | I2: LIMA | J2: 22 | K2: 1 | L2: 1 | M2: 1 | N2: 1 | O2: 1 | P2: 1 | Q2: 16 | R2: 5 | S2: 21 | T2: 9 | U2: 1 | V2: 1 | W2: 1 | X2: 1 | Y2: 0 | Z2: 0 | AA2: 0 | AB2: 0 | AC2: 1 | AD2: 0 | AE2: 1 | AF2: 1 | AG2: 0 | AH2: 0 | AI2: 0 | AK2: 0 | AL2: 7 | AM2: 0.7 | AN2: 0.3 | AO2: 1 | AP2: 1200 | AQ2: 1200
A3: 77078190-1 | B3: 44389 | C3: VET | D3: Counter | E3: Counter | F3: ARACELI TARAZONA SERNAQUE | G3: GISELA AVELLANEDA CAMACHO | H3: LIMA OLIVOS | I3: LIMA | J3: 22 | K3: 1 | L3: 1 | M3: 1 | N3: 1 | O3: 1 | P3: 1 | Q3: 16 | R3: 5 | S3: 21 | T3: 9 | U3: 2 | V3: 2 | W3: 2 | X3: 3 | Y3: 0 | Z3: 0 | AA3: 0 | AB3: 0 | AC3: 0 | AD3: 0 | AE3: 0 | AF3: 0 | AG3: 0 | AH3: 0 | AI3: 0 | AK3: 0 | AL3: 9 | AM3: 0.7 | AN3: 0.3 | AO3: 1 | AP3: 1200 | AQ3: 1200
A4: 47567126-6 | B4: 43724 | C4: VET | D4: Counter | E4: Counter | F4: ARACELI TARAZONA SERNAQUE | G4: GISELA AVELLANEDA CAMACHO | H4: LIMA COMAS | I4: LIMA | J4: 11 | K4: 0 | L4: 0 | M4: 1 | N4: 1 | O4: 0.5 | P4: 0.5 | Q4: 6 | R4: 2 | S4: 8 | T4: 4 | U4: 0 | V4: 0 | W4: 0 | X4: 0 | Y4: 0 | Z4: 0 | AA4: 0 | AB4: 0 | AC4: 0 | AD4: 0 | AE4: 0 | AF4: 0 | AG4: 0 | AH4: 0 | AI4: 0 | AK4: 0 | AL4: 0 | AM4: 0.7 | AN4: 0.3 | AO4: 0.5 | AP4: 1200 | AQ4: 600
A5: 41710085-2 | B5: 45992 | C5: M9 | D5: Counter | E5: Counter | F5: ARACELI TARAZONA SERNAQUE | G5: GISELA AVELLANEDA CAMACHO | H5: LIMA OLIVOS | I5: LIMA | J5: 12 | K5: 1 | L5: 1 | M5: 0.18181818 | N5: 0 | O5: 0.54545455 | P5: 0.54545455 | Q5: 9 | R5: 2 | S5: 11 | T5: 5 | U5: 1 | V5: 1 | W5: 0 | X5: 0 | Y5: 0 | Z5: 0 | AA5: 0 | AB5: 0 | AC5: 0 | AD5: 0 | AE5: 0 | AF5: 0 | AG5: 2 | AH5: 1 | AI5: 0 | AK5: 0 | AL5: 5 | AM5: 0.7 | AN5: 0.3 | AO5: 0.54545455 | AP5: 1200 | AQ5: 655
A6: 42763046-9 | B6: 44361 | C6: VET | D6: Counter | E6: Counter | F6: ARACELI TARAZONA SERNAQUE | G6: GISELA AVELLANEDA CAMACHO | H6: LIMA OLIVOS | I6: LIMA | J6: 22 | K6: 1 | L6: 1 | M6: 1 | N6: 1 | O6: 1 | P6: 1 | Q6: 16 | R6: 5 | S6: 21 | T6: 8 | U6: 2 | V6: 2 | W6: 2 | X6: 3 | Y6: 0 | Z6: 1 | AA6: 1 | AB6: 1 | AC6: 0 | AD6: 0 | AE6: 0 | AF6: 0 | AG6: 1 | AH6: 1 | AI6: 0 | AK6: 0 | AL6: 14 | AM6: 0.7 | AN6: 0.3 | AO6: 1 | AP6: 1200 | AQ6: 1200
A7: 41907916-8 | B7: 45026 | C7: VET | D7: Counter | E7: Counter | F7: ARACELI TARAZONA SERNAQUE | G7: GISELA AVELLANEDA CAMACHO | H7: LIMA COMAS | I7: LIMA | J7: 22 | K7: 1 | L7: 1 | M7: 1 | N7: 1 | O7: 1 | P7: 1 | Q7: 12 | R7: 3 | S7: 15 | T7: 6 | U7: 0 | V7: 0 | W7: 0 | X7: 0 | Y7: 0 | Z7: 0 | AA7: 0 | AB7: 0 | AC7: 0 | AD7: 0 | AE7: 0 | AF7: 0 | AG7: 0 | AH7: 1 | AI7: 0 | AK7: 0 | AL7: 1 | AM7: 0.7 | AN7: 0.3 | AO7: 1 | AP7: 1200 | AQ7: 1200
A8: 46569779-8 | B8: 45383 | C8: VET | D8: Counter | E8: Counter | F8: ARACELI TARAZONA SERNAQUE | G8: GISELA AVELLANEDA CAMACHO | H8: LIMA OLIVOS | I8: LIMA | J8: 10 | K8: 0 | L8: 0 | M8: 0.81818182 | N8: 1 | O8: 0.45454545 | P8: 0.45454545 | Q8: 8 | R8: 2 | S8: 10 | T8: 3 | U8: 0 | V8: 0 | W8: 0 | X8: 0 | Y8: 0 | Z8: 0 | AA8: 0 | AB8: 0 | AC8: 0 | AD8: 0 | AE8: 0 | AF8: 0 | AG8: 0 | AH8: 0 | AI8: 0 | AK8: 0 | AL8: 0 | AM8: 0.7 | AN8: 0.3 | AO8: 0.45454545 | AP8: 1200 | AQ8: 545
A9: 46349775-9 | B9: 44214 | C9: VET | D9: Counter | E9: Counter | F9: ARACELI TARAZONA SERNAQUE | G9: GISELA AVELLANEDA CAMACHO | H9: LIMA COMAS | I9: LIMA | J9: 11 | K9: 1 | L9: 1 | M9: 0 | N9: 0 | O9: 0.5 | P9: 0.5 | Q9: 6 | R9: 2 | S9: 8 | T9: 3 | U9: 2 | V9: 2 | W9: 0 | X9: 0 | Y9: 0 | Z9: 0 | AA9: 0 | AB9: 0 | AC9: 0 | AD9: 0 | AE9: 0 | AF9: 0 | AG9: 0 | AH9: 0 | AI9: 0 | AK9: 1 | AL9: 5 | AM9: 0.7 | AN9: 0.3 | AO9: 0.5 | AP9: 1200 | AQ9: 600
A10: 25831501-0 | B10: 45139 | C10: VET | D10: Counter | E10: Counter | F10: JENNY ALEJANDRA DE LA CRUZ FLORES | G10: GISELA AVELLANEDA CAMACHO | H10: LIMA ATE | I10: LIMA | J10: 10 | K10: 0 | L10: 0 | M10: 0.81818182 | N10: 1 | O10: 0.45454545 | P10: 0.45454545 | Q10: 8 | R10: 2 | S10: 10 | T10: 4 | U10: 0 | V10: 0 | W10: 0 | X10: 0 | Y10: 0 | Z10: 0 | AA10: 0 | AB10: 0 | AC10: 0 | AD10: 0 | AE10: 0 | AF10: 0 | AG10: 0 | AH10: 0 | AI10: 0 | AK10: 0 | AL10: 0 | AM10: 0.7 | AN10: 0.3 | AO10: 0.45454545 | AP10: 1200 | AQ10: 545
A11: 45172927-1 | B11: 46146 | C11: M4 | D11: Counter | E11: Counter | F11: JENNY ALEJANDRA DE LA CRUZ FLORES | G11: GISELA AVELLANEDA CAMACHO | H11: LIMA BREÑA | I11: LIMA | J11: 22 | K11: 1 | L11: 1 | M11: 1 | N11: 1 | O11: 1 | P11: 1 | Q11: 13 | R11: 4 | S11: 17 | T11: 5 | U11: 0 | V11: 0 | W11: 0 | X11: 0 | Y11: 0 | Z11: 1 | AA11: 1 | AB11: 1 | AC11: 0 | AD11: 0 | AE11: 0 | AF11: 0 | AG11: 2 | AH11: 0 | AI11: 0 | AK11: 0 | AL11: 4 | AM11: 0.7 | AN11: 0.3 | AO11: 1 | AP11: 1200 | AQ11: 1200
A12: 70862248-1 | B12: 44214 | C12: VET | D12: Counter | E12: Counter | F12: JENNY ALEJANDRA DE LA CRUZ FLORES | G12: GISELA AVELLANEDA CAMACHO | H12: LIMA ATE | I12: LIMA | J12: 12 | K12: 1 | L12: 1 | M12: 0.18181818 | N12: 0 | O12: 0.54545455 | P12: 0.54545455 | Q12: 9 | R12: 3 | S12: 12 | T12: 3 | U12: 1 | V12: 1 | W12: 0 | X12: 0 | Y12: 0 | Z12: 2 | AA12: 0 | AB12: 0 | AC12: 0 | AD12: 0 | AE12: 0 | AF12: 0 | AG12: 3 | AH12: 2 | AI12: 0 | AK12: 0 | AL12: 6 | AM12: 0.7 | AN12: 0.3 | AO12: 0.54545455 | AP12: 1200 | AQ12: 655
A13: 46824537-5 | B13: 44228 | C13: VET | D13: Counter | E13: Counter | F13: JENNY ALEJANDRA DE LA CRUZ FLORES | G13: GISELA AVELLANEDA CAMACHO | H13: LIMA BREÑA | I13: LIMA | J13: 12 | K13: 1 | L13: 1 | M13: 0.18181818 | N13: 0 | O13: 0.54545455 | P13: 0.54545455 | Q13: 7 | R13: 2 | S13: 9 | T13: 4 | U13: 0 | V13: 0 | W13: 0 | X13: 0 | Y13: 0 | Z13: 0 | AA13: 0 | AB13: 0 | AC13: 0 | AD13: 0 | AE13: 0 | AF13: 0 | AG13: 1 | AH13: 1 | AI13: 0 | AK13: 0 | AL13: 2 | AM13: 0.7 | AN13: 0.3 | AO13: 0.54545455 | AP13: 1200 | AQ13: 655
... A236: 45021034-5 | B236: 46113 | C236: M5 | D236: Outbound | E236: Outbound Premium | F236: VERONICA SANTILLAN SALAZAR | G236: JOSE ANGELATS AGREDA | H236: TRUJILLO | I236: TRUJILLO | J236: 22 | K236: 1 | L236: 1 | M236: 1 | N236: 1 | O236: 1 | P236: 1 | Q236: 6 | R236: 2 | S236: 8 | T236: 4 | U236: 0 | V236: 0 | W236: 0 | X236: 0 | Y236: 0 | Z236: 0 | AA236: 0 | AB236: 0 | AC236: 0 | AD236: 0 | AE236: 0 | AF236: 0 | AG236: 0 | AH236: 0 | AI236: 0 | AK236: 0 | AL236: 0 | AM236: 0.7 | AN236: 0.3 | AO236: 1 | AP236: 1200 | AQ236: 1200
A237: 73782028-4 | B237: 46113 | C237: M5 | D237: Outbound | E237: Lima Sur | F237: LILIANA SEJO SUAREZ | G237: JOSUE MORA SOLSOL | H237: Lima Sur | I237: LIMA | J237: 22 | K237: 1 | L237: 1 | M237: 1 | N237: 1 | Q237: 5 | S237: 5 | T237: 10 | U237: 1 | V237: 1 | W237: 1 | X237: 1 | Y237: 0 | Z237: 0 | AA237: 0 | AB237: 0 | AC237: 0 | AD237: 0 | AE237: 0 | AF237: 0 | AG237: 0 | AH237: 0 | AI237: 0 | AK237: 0 | AL237: 4
A238: 48036149-6 | B238: 46113 | C238: M5 | D238: Outbound | E238: Lima Sur | F238: LILIANA SEJO SUAREZ | G238: JOSUE MORA SOLSOL | H238: Lima Sur | I238: LIMA | J238: 22 | K238: 1 | L238: 1 | M238: 1 | N238: 1 | Q238: 5 | S238: 5 | T238: 3 | U238: 0 | V238: 0 | W238: 0 | X238: 0 | Y238: 0 | Z238: 0 | AA238: 0 | AB238: 0 | AC238: 0 | AD238: 0 | AE238: 0 | AF238: 0 | AG238: 0 | AH238: 0 | AI238: 0 | AK238: 0 | AL238: 0
A239: 76494409-2 | B239: 46113 | C239: M5 | D239: Outbound | E239: Lima Sur | F239: LILIANA SEJO SUAREZ | G239: JOSUE MORA SOLSOL | H239: Lima Sur | I239: LIMA | J239: 22 | K239: 1 | L239: 1 | M239: 1 | N239: 1 | Q239: 5 | S239: 5 | T239: 15 | U239: 1 | V239: 1 | W239: 1 | X239: 1 | Y239: 0 | Z239: 0 | AA239: 0 | AB239: 0 | AC239: 0 | AD239: 0 | AE239: 0 | AF239: 0 | AG239: 0 | AH239: 0 | AI239: 0 | AK239: 0 | AL239: 4
A240: 75686214-1 | B240: 46113 | C240: M5 | D240: Outbound | E240: Lima Sur | F240: LILIANA SEJO SUAREZ | G240: JOSUE MORA SOLSOL | H240: Lima Sur | I240: LIMA | J240: 22 | K240: 1 | L240: 1 | M240: 1 | N240: 1 | Q240: 5 | S240: 5 | T240: 16 | U240: 1 | V240: 1 | W240: 1 | X240: 1 | Y240: 0 | Z240: 3 | AA240: 2 | AB240: 3 | AC240: 0 | AD240: 0 | AE240: 0 | AF240: 0 | AG240: 0 | AH240: 0 | AI240: 0 | AK240: 0 | AL240: 12
A241: 46385234-6 | B241: 45078 | C241: VET | D241: Outbound | E241: Lima Sur | F241: LILIANA SEJO SUAREZ | G241: JOSUE MORA SOLSOL | H241: Lima Sur | I241: LIMA | J241: 5.5 | K241: 0 | L241: 0 | M241: 0 | N241: 1 | Q241: 2 | S241: 2 | T241: 6 | U241: 0 | V241: 0 | W241: 0 | X241: 0 | Y241: 0 | Z241: 0 | AA241: 0 | AB241: 0 | AC241: 0 | AD241: 0 | AE241: 0 | AF241: 0 | AG241: 0 | AH241: 0 | AI241: 0 | AK241: 0 | AL241: 0
A242: 72505244-3 | B242: 46113 | C242: M5 | D242: Outbound | E242: Lima Sur | F242: MARITZA HUAMAN NAVARRO | G242: JOSUE MORA SOLSOL | H242: Lima Sur | I242: LIMA | J242: 22 | K242: 1 | L242: 1 | M242: 1 | N242: 1 | Q242: 5 | S242: 5 | T242: 10 | U242: 2 | V242: 2 | W242: 2 | X242: 3 | Y242: 0 | Z242: 0 | AA242: 0 | AB242: 0 | AC242: 0 | AD242: 0 | AE242: 0 | AF242: 0 | AG242: 0 | AH242: 0 | AI242: 0 | AK242: 0 | AL242: 9
A243: 70067394-0 | B243: 46113 | C243: M5 | D243: Outbound | E243: Lima Sur | F243: MARITZA HUAMAN NAVARRO | G243: JOSUE MORA SOLSOL | H243: Lima Sur | I243: LIMA | J243: 22 | K243: 1 | L243: 1 | M243: 1 | N243: 1 | Q243: 5 | S243: 5 | T243: 8 | U243: 0 | V243: 0 | W243: 0 | X243: 0 | Y243: 0 | Z243: 0 | AA243: 0 | AB243: 0 | AC243: 0 | AD243: 0 | AE243: 0 | AF243: 0 | AG243: 0 | AH243: 0 | AI243: 0 | AK243: 0 | AL243: 0
A244: 75841750-1 | B244: 46113 | C244: M5 | D244: Outbound | E244: Lima Sur | F244: MARITZA HUAMAN NAVARRO | G244: JOSUE MORA SOLSOL | H244: Lima Sur | I244: LIMA | J244: 22 | K244: 1 | L244: 1 | M244: 1 | N244: 1 | Q244: 5 | S244: 5 | T244: 8 | U244: 0 | V244: 0 | W244: 0 | X244: 0 | Y244: 0 | Z244: 0 | AA244: 0 | AB244: 0 | AC244: 0 | AD244: 0 | AE244: 0 | AF244: 0 | AG244: 0 | AH244: 0 | AI244: 0 | AK244: 0 | AL244: 0
A245: 76199458-7 | B245: 46113 | C245: M5 | D245: Outbound | E245: Lima Sur | F245: MARITZA HUAMAN NAVARRO | G245: JOSUE MORA SOLSOL | H245: Lima Sur | I245: LIMA | J245: 22 | K245: 1 | L245: 1 | M245: 1 | N245: 1 | Q245: 5 | S245: 5 | T245: 8 | U245: 1 | V245: 1 | W245: 1 | X245: 1 | Y245: 0 | Z245: 0 | AA245: 0 | AB245: 0 | AC245: 0 | AD245: 0 | AE245: 0 | AF245: 0 | AG245: 0 | AH245: 0 | AI245: 0 | AK245: 0 | AL245: 4
A246: 76656036-4 | B246: 44867 | C246: VET | D246: Inbound | E246: Lima Sur | F246: NINO BELLIDO VALENZUELA | G246: JOSUE MORA SOLSOL | H246: Lima Sur | I246: LIMA | J246: 22 | K246: 1 | L246: 1 | M246: 1 | N246: 1 | Q246: 8 | S246: 8 | T246: 4 | U246: 0 | V246: 0 | W246: 0 | X246: 0 | Y246: 0 | Z246: 0 | AA246: 0 | AB246: 0 | AC246: 0 | AD246: 0 | AE246: 0 | AF246: 0 | AG246: 0 | AH246: 1 | AI246: 0 | AK246: 0 | AL246: 1
A247: 75628851-8 | B247: 44746 | C247: VET | D247: Inbound | E247: Lima Sur | F247: NINO BELLIDO VALENZUELA | G247: JOSUE MORA SOLSOL | H247: Lima Sur | I247: LIMA | J247: 22 | K247: 1 | L247: 1 | M247: 1 | N247: 1 | Q247: 8 | S247: 8 | T247: 4 | U247: 2 | V247: 2 | W247: 2 | X247: 3 | Y247: 0 | Z247: 1 | AA247: 1 | AB247: 1 | AC247: 0 | AD247: 0 | AE247: 0 | AF247: 0 | AG247: 0 | AH247: 0 | AI247: 0 | AK247: 0 | AL247: 12
A248: 48205433-7 | B248: 45019 | C248: VET | D248: Inbound | E248: Lima Sur | F248: NINO BELLIDO VALENZUELA | G248: JOSUE MORA SOLSOL | H248: Lima Sur | I248: LIMA | J248: 11 | K248: 1 | L248: 1 | M248: 0 | N248: 0 | Q248: 4 | S248: 4 | T248: 2 | U248: 1 | V248: 1 | W248: 0 | X248: 0 | Y248: 0 | Z248: 0 | AA248: 0 | AB248: 0 | AC248: 0 | AD248: 0 | AE248: 0 | AF248: 0 | AG248: 0 | AH248: 1 | AI248: 0 | AK248: 0 | AL248: 2
... A264: 48768139-9 | B264: 46204 | C264: M2 | D264: Outbound | E264: Lima Sur | F264: MARITZA HUAMAN NAVARRO | G264: JOSUE MORA SOLSOL | H264: Lima Sur | I264: LIMA | J264: 22 | K264: 1 | L264: 1 | M264: 1 | N264: 1 | Q264: 3 | S264: 3 | T264: 2 | U264: 0 | V264: 0 | W264: 0 | X264: 0 | Y264: 0 | Z264: 0 | AA264: 0 | AB264: 0 | AC264: 0 | AD264: 0 | AE264: 0 | AF264: 0 | AG264: 0 | AH264: 0 | AI264: 0 | AK264: 0 | AL264: 0

Sheet tablas
B2: Niveles | C2: Cumplimiento | D2: Acelerador
B3: N1 | C3: 0.8 | D3: 0.3
B4: N2 | C4: 0.9 | D4: 0.9
B5: N3 | C5: 1 | D5: 1
B6: N4 | C6: 1.1 | D6: 1.3
B7: N5 | C7: 1.2 | D7: 1.5
B8: N6 | C8: 1.3 | D8: 2
B9: No activa
